spectreapi/__init__.py
spectreapi/collector.py
spectreapi/response.py
spectreapi/server.py
spectreapi/spectre.py
spectreapi/zone.py
spectre_api-0.5.5.dist-info/LICENSE
spectre_api-0.5.5.dist-info/METADATA
spectre_api-0.5.5.dist-info/WHEEL
spectre_api-0.5.5.dist-info/top_level.txt
spectre_api-0.5.5.dist-info/RECORD
