Metadata-Version: 2.1
Name: spectre-api
Version: 0.5.5
Summary: Wrapper to use the Lumeta Spectre API
Home-page: UNKNOWN
License: MIT
Platform: UNKNOWN
License-File: LICENSE
Requires-Dist: requests
